{
  "generated_at": "2026-07-15T20:04:46.772657+00:00",
  "repo_id": "R_kgDOTXasIg",
  "categories": [
    {
      "id": "DIC_kwDOTXasIs4DBIEC",
      "name": "Announcements",
      "emoji": ":mega:",
      "slug": "announcements"
    },
    {
      "id": "DIC_kwDOTXasIs4DBIED",
      "name": "General",
      "emoji": ":speech_balloon:",
      "slug": "general"
    },
    {
      "id": "DIC_kwDOTXasIs4DBIEF",
      "name": "Ideas",
      "emoji": ":bulb:",
      "slug": "ideas"
    },
    {
      "id": "DIC_kwDOTXasIs4DBIEH",
      "name": "Polls",
      "emoji": ":ballot_box:",
      "slug": "polls"
    },
    {
      "id": "DIC_kwDOTXasIs4DBIEE",
      "name": "Q&A",
      "emoji": ":pray:",
      "slug": "q-a"
    },
    {
      "id": "DIC_kwDOTXasIs4DBIEG",
      "name": "Show and tell",
      "emoji": ":raised_hands:",
      "slug": "show-and-tell"
    }
  ],
  "discussions": []
}